hobby_by_category/__init__.py
hobby_by_category/data.py
hobby_by_category/utils.py
hobby_by_category-1.0.0.dist-info/licenses/LICENSE
hobby_by_category-1.0.0.dist-info/METADATA
hobby_by_category-1.0.0.dist-info/WHEEL
hobby_by_category-1.0.0.dist-info/top_level.txt
hobby_by_category-1.0.0.dist-info/RECORD
