Metadata-Version: 2.4
Name: hobby-by-category
Version: 1.0.0
Summary: Categorized list of hobbies
Home-page: https://github.com/therealMAO247/hobby-by-category-py
Author: Michael Anan Onimisi
Author-email: 247@therealMAO.com
License: MIT
Classifier: Programming Language :: Python :: 3
Classifier: License :: OSI Approved :: MIT License
Classifier: Operating System :: OS Independent
Requires-Python: >=3.6
License-File: LICENSE
Dynamic: author
Dynamic: author-email
Dynamic: classifier
Dynamic: description
Dynamic: description-content-type
Dynamic: home-page
Dynamic: license
Dynamic: license-file
Dynamic: requires-python
Dynamic: summary
